easyctypes/__init__.py
easyctypes/devices.py
easyctypes/mouse_control.py
easyctypes-0.1.6.dist-info/LICENSE
easyctypes-0.1.6.dist-info/METADATA
easyctypes-0.1.6.dist-info/WHEEL
easyctypes-0.1.6.dist-info/top_level.txt
easyctypes-0.1.6.dist-info/RECORD
