Metadata-Version: 2.1
Name: easyctypes
Version: 0.1.6
Summary: A ctypes-based module for advanced mouse control and device access
Home-page: https://github.com/ftnick/easyctypes
Author: ftnick
Author-email: 
License: MIT
Classifier: Programming Language :: Python :: 3.9
Classifier: Operating System :: OS Independent
Requires-Python: >=3.9
License-File: LICENSE
Provides-Extra: dev
Requires-Dist: pytest; extra == "dev"
Requires-Dist: tox; extra == "dev"
Requires-Dist: coverage; extra == "dev"
Requires-Dist: flake8; extra == "dev"
